kp_tools/__init__.py
kp_tools/process_braker.py
kp_tools-0.1.1.dist-info/LICENSE
kp_tools-0.1.1.dist-info/METADATA
kp_tools-0.1.1.dist-info/WHEEL
kp_tools-0.1.1.dist-info/entry_points.txt
kp_tools-0.1.1.dist-info/top_level.txt
kp_tools-0.1.1.dist-info/RECORD
